publicationpackage/__init__.py
publicationpackage/get_database_info.py
publicationpackage/load_data.py
publicationpackage/load_table_from_catalog.py
publicationpackage/run_sql.py
publicationpackage/write_dataframe_to_s3.py
publicationpackage-0.0.6.dist-info/METADATA
publicationpackage-0.0.6.dist-info/WHEEL
publicationpackage-0.0.6.dist-info/RECORD
