Metadata-Version: 2.1
Name: publicationpackage
Version: 0.0.6
Summary: This package contains the functions needed for doing a publication in a Jupyter Notebook.
Author: Jesse Faber
Author-email: Jesse.Faber@aegon.nl
Requires-Python: >=3.9,<4.0
Classifier: Programming Language :: Python :: 3
Classifier: Programming Language :: Python :: 3.9
Classifier: Programming Language :: Python :: 3.10
Classifier: Programming Language :: Python :: 3.11
Classifier: Programming Language :: Python :: 3.12
Requires-Dist: awsglue-dev (>=2021.12.30,<2022.0.0)
Requires-Dist: boto3 (>=1.34.15,<2.0.0)
Requires-Dist: pyspark (>=3.5.0,<4.0.0)
